mkdocstrings_handlers/matlab/__init__.py
mkdocstrings_handlers/matlab/config.py
mkdocstrings_handlers/matlab/handler.py
mkdocstrings_handlers/matlab/py.typed
mkdocstrings_handlers/matlab/rendering.py
mkdocstrings_handlers/matlab/templates/material/attributes.html.jinja
mkdocstrings_handlers/matlab/templates/material/backlinks.html.jinja
mkdocstrings_handlers/matlab/templates/material/children.html.jinja
mkdocstrings_handlers/matlab/templates/material/class.html.jinja
mkdocstrings_handlers/matlab/templates/material/docstring.html.jinja
mkdocstrings_handlers/matlab/templates/material/expression.html.jinja
mkdocstrings_handlers/matlab/templates/material/folder.html.jinja
mkdocstrings_handlers/matlab/templates/material/function.html.jinja
mkdocstrings_handlers/matlab/templates/material/language.html.jinja
mkdocstrings_handlers/matlab/templates/material/namespace.html.jinja
mkdocstrings_handlers/matlab/templates/material/property.html.jinja
mkdocstrings_handlers/matlab/templates/material/script.html.jinja
mkdocstrings_handlers/matlab/templates/material/signature.html.jinja
mkdocstrings_handlers/matlab/templates/material/style.css
mkdocstrings_handlers/matlab/templates/material/summary.html.jinja
mkdocstrings_handlers/matlab/templates/material/docstring/admonition.html.jinja
mkdocstrings_handlers/matlab/templates/material/docstring/classes.html.jinja
mkdocstrings_handlers/matlab/templates/material/docstring/examples.html.jinja
mkdocstrings_handlers/matlab/templates/material/docstring/functions.html.jinja
mkdocstrings_handlers/matlab/templates/material/docstring/input_arguments.html.jinja
mkdocstrings_handlers/matlab/templates/material/docstring/name_value_arguments.html.jinja
mkdocstrings_handlers/matlab/templates/material/docstring/namespaces.html.jinja
mkdocstrings_handlers/matlab/templates/material/docstring/output_arguments.html.jinja
mkdocstrings_handlers/matlab/templates/material/docstring/properties.html.jinja
mkdocstrings_matlab-1.1.0.dist-info/METADATA
mkdocstrings_matlab-1.1.0.dist-info/WHEEL
mkdocstrings_matlab-1.1.0.dist-info/licenses/LICENSE
mkdocstrings_matlab-1.1.0.dist-info/RECORD
