Metadata-Version: 2.4
Name: mkdocstrings-matlab
Version: 1.1.0
Summary: A MATLAB handler for mkdocstrings
Author-email: Mark Hu <watermarkhu@gmail.com>
License: MIT
License-File: LICENSE
Classifier: Development Status :: 4 - Beta
Classifier: Intended Audience :: Developers
Classifier: Programming Language :: Python
Classifier: Programming Language :: Python :: 3
Classifier: Programming Language :: Python :: 3 :: Only
Classifier: Programming Language :: Python :: 3.10
Classifier: Programming Language :: Python :: 3.11
Classifier: Programming Language :: Python :: 3.12
Classifier: Programming Language :: Python :: 3.13
Classifier: Programming Language :: Python :: 3.14
Classifier: Topic :: Documentation
Classifier: Topic :: Software Development
Classifier: Topic :: Software Development :: Documentation
Classifier: Topic :: Utilities
Classifier: Typing :: Typed
Requires-Python: <3.15,>=3.10
Requires-Dist: charset-normalizer~=3.4
Requires-Dist: griffe~=1.15.0
Requires-Dist: maxx~=0.6.0
Requires-Dist: mkdocs-autorefs~=1.4
Requires-Dist: mkdocstrings~=0.29
Requires-Dist: typing-extensions>=4.0; python_version < '3.11'
